fp2_unpacker.v
module fp2_e1m0_to_reram_unpacker (
    input wire clk,
    input wire rst,
    
    // 4-bit FP2 Block Inputs
    input wire S,   // Shared Sign
    input wire E,   // Shared Exponent
    input wire C1,  // Flag for W1
    input wire C2,  // Flag for W2
    
    // Unpacked Outputs for W1 DAC
    output reg Dir1,
    output reg Mag1_1, // Represents 1.0
    output reg Mag1_0, // Represents 0.5
    
    // Unpacked Outputs for W2 DAC
    output reg Dir2,
    output reg Mag2_1, // Represents 1.0
    output reg Mag2_0, // Represents 0.5
    
    // Terminal count register
    output reg [7:0] y 
);

    // Combinational logic for W1 unpacking
    wire w_Dir1   = S & C1;
    wire w_Mag1_1 = C1 & E;
    wire w_Mag1_0 = C1 & ~E;

    // Combinational logic for W2 unpacking
    wire w_Dir2   = S & C2;
    wire w_Mag2_1 = C2 & E;
    wire w_Mag2_0 = C2 & ~E;

    // Synchronous clocked output block
    always @(posedge clk or posedge rst) begin
        if (rst) begin
            y       <= 8'b0;
            Dir1    <= 1'b0;
            Mag1_1  <= 1'b0;
            Mag1_0  <= 1'b0;
            Dir2    <= 1'b0;
            Mag2_1  <= 1'b0;
            Mag2_0  <= 1'b0;
        end else begin
            // Increment terminal count register per clock cycle
            y       <= y + 1; 
            
            // Register DAC inputs
            Dir1    <= w_Dir1;
            Mag1_1  <= w_Mag1_1;
            Mag1_0  <= w_Mag1_0;
            Dir2    <= w_Dir2;
            Mag2_1  <= w_Mag2_1;
            Mag2_0  <= w_Mag2_0;
        end
    end

endmodule

tb_unpacker.v
`timescale 1ns/1ps

module tb_unpacker;

    reg clk, rst;
    reg S, E, C1, C2;
    wire Dir1, Mag1_1, Mag1_0;
    wire Dir2, Mag2_1, Mag2_0;
    wire [7:0] y;

    integer i;
    integer errors;

    // Expected values, computed from the SAME combinational equations as the
    // DUT so we're checking timing/registration, not re-deriving the encoding.
    // (A truly independent check would hand-encode the FP2-E1M0 truth table.)
    reg exp_Dir1, exp_Mag1_1, exp_Mag1_0;
    reg exp_Dir2, exp_Mag2_1, exp_Mag2_0;

    fp2_e1m0_to_reram_unpacker dut (
        .clk    (clk),
        .rst    (rst),
        .S      (S),
        .E      (E),
        .C1     (C1),
        .C2     (C2),
        .Dir1   (Dir1),
        .Mag1_1 (Mag1_1),
        .Mag1_0 (Mag1_0),
        .Dir2   (Dir2),
        .Mag2_1 (Mag2_1),
        .Mag2_0 (Mag2_0),
        .y      (y)
    );

    // 100MHz clock
    always #5 clk = ~clk;

    initial begin
        $dumpfile("unpacker.vcd");
        $dumpvars(0, tb_unpacker);

        clk = 0; rst = 1;
        S = 0; E = 0; C1 = 0; C2 = 0;
        errors = 0;

        @(posedge clk); @(posedge clk);
        rst = 0;

        // Drive all 16 combinations of {S,E,C1,C2}, one per clock, and check
        // the registered outputs one cycle later (outputs are clocked).
        for (i = 0; i < 16; i = i + 1) begin
            @(negedge clk);
            {S, E, C1, C2} = i[3:0];
        end

        // let the last vector propagate through the register, then finish
        @(negedge clk);
        @(negedge clk);
        $display("--------------------------------------------------");
        if (errors == 0)
            $display("RESULT: ALL CHECKS PASSED");
        else
            $display("RESULT: %0d CHECK(S) FAILED", errors);
        $finish;
    end

    // Independent (hand-written) reference model of the FP2-E1M0 truth table,
    // sampled at the same point the inputs are applied, then compared to the
    // DUT's registered output one clock later.
    reg S_d, E_d, C1_d, C2_d;
    always @(posedge clk) begin
        S_d  <= S;
        E_d  <= E;
        C1_d <= C1;
        C2_d <= C2;
    end

    always @(posedge clk) begin
        if (!rst) begin
            // Compare DUT outputs (reflecting inputs sampled last cycle)
            // against the hand-coded truth table for those same inputs.
            exp_Dir1   = S_d & C1_d;
            exp_Mag1_1 = C1_d & E_d;
            exp_Mag1_0 = C1_d & ~E_d;
            exp_Dir2   = S_d & C2_d;
            exp_Mag2_1 = C2_d & E_d;
            exp_Mag2_0 = C2_d & ~E_d;

            if ({Dir1, Mag1_1, Mag1_0, Dir2, Mag2_1, Mag2_0} !==
                {exp_Dir1, exp_Mag1_1, exp_Mag1_0, exp_Dir2, exp_Mag2_1, exp_Mag2_0}) begin
                errors = errors + 1;
                $display("MISMATCH at t=%0t: in{S=%b E=%b C1=%b C2=%b} -> got{Dir1=%b M1_1=%b M1_0=%b Dir2=%b M2_1=%b M2_0=%b} exp{Dir1=%b M1_1=%b M1_0=%b Dir2=%b M2_1=%b M2_0=%b}",
                    $time, S_d, E_d, C1_d, C2_d,
                    Dir1, Mag1_1, Mag1_0, Dir2, Mag2_1, Mag2_0,
                    exp_Dir1, exp_Mag1_1, exp_Mag1_0, exp_Dir2, exp_Mag2_1, exp_Mag2_0);
            end else begin
                $display("OK      at t=%0t: in{S=%b E=%b C1=%b C2=%b} -> {Dir1=%b M1_1=%b M1_0=%b Dir2=%b M2_1=%b M2_0=%b}",
                    $time, S_d, E_d, C1_d, C2_d, Dir1, Mag1_1, Mag1_0, Dir2, Mag2_1, Mag2_0);
            end
        end
    end

endmodule

unpacker.vcd
$date
	Tue Jul 21 12:09:51 2026
$end
$version
	Icarus Verilog
$end
$timescale
	1ps
$end
$scope module tb_unpacker $end
$var wire 8 ! y [7:0] $end
$var wire 1 " Mag2_1 $end
$var wire 1 # Mag2_0 $end
$var wire 1 $ Mag1_1 $end
$var wire 1 % Mag1_0 $end
$var wire 1 & Dir2 $end
$var wire 1 ' Dir1 $end
$var reg 1 ( C1 $end
$var reg 1 ) C1_d $end
$var reg 1 * C2 $end
$var reg 1 + C2_d $end
$var reg 1 , E $end
$var reg 1 - E_d $end
$var reg 1 . S $end
$var reg 1 / S_d $end
$var reg 1 0 clk $end
$var reg 1 1 exp_Dir1 $end
$var reg 1 2 exp_Dir2 $end
$var reg 1 3 exp_Mag1_0 $end
$var reg 1 4 exp_Mag1_1 $end
$var reg 1 5 exp_Mag2_0 $end
$var reg 1 6 exp_Mag2_1 $end
$var reg 1 7 rst $end
$var integer 32 8 errors [31:0] $end
$var integer 32 9 i [31:0] $end
$scope module dut $end
$var wire 1 ( C1 $end
$var wire 1 * C2 $end
$var wire 1 , E $end
$var wire 1 . S $end
$var wire 1 0 clk $end
$var wire 1 7 rst $end
$var wire 1 : w_Dir1 $end
$var wire 1 ; w_Dir2 $end
$var wire 1 < w_Mag1_0 $end
$var wire 1 = w_Mag1_1 $end
$var wire 1 > w_Mag2_0 $end
$var wire 1 ? w_Mag2_1 $end
$var reg 1 ' Dir1 $end
$var reg 1 & Dir2 $end
$var reg 1 % Mag1_0 $end
$var reg 1 $ Mag1_1 $end
$var reg 1 # Mag2_0 $end
$var reg 1 " Mag2_1 $end
$var reg 8 @ y [7:0] $end
$upscope $end
$upscope $end
$enddefinitions $end
#0
$dumpvars
b0 @
0?
0>
0=
0<
0;
0:
bx 9
b0 8
17
x6
x5
x4
x3
x2
x1
00
x/
0.
x-
0,
x+
0*
x)
0(
0'
0&
0%
0$
0#
0"
b0 !
$end
#5000
0+
0)
0-
0/
10
#10000
00
#15000
b1 !
b1 @
05
06
02
03
04
01
b0 9
07
10
#20000
b1 9
00
#25000
b10 !
b10 @
10
#30000
1>
b10 9
1*
00
#35000
1#
b11 !
b11 @
1+
10
#40000
1<
0>
b11 9
1(
0*
00
#45000
0#
1%
b100 !
b100 @
0+
1)
15
10
#50000
1>
b100 9
1*
00
#55000
1#
b101 !
b101 @
1+
05
13
10
#60000
0<
0>
b101 9
1,
0(
0*
00
#65000
0#
0%
b110 !
b110 @
0+
0)
1-
15
10
#70000
1?
b110 9
1*
00
#75000
1"
b111 !
b111 @
1+
05
03
10
#80000
1=
0?
b111 9
1(
0*
00
#85000
0"
1$
b1000 !
b1000 @
0+
1)
16
10
#90000
1?
b1000 9
1*
00
#95000
1"
b1001 !
b1001 @
1+
06
14
10
#100000
0=
0?
b1001 9
1.
0,
0(
0*
00
#105000
0"
0$
b1010 !
b1010 @
0+
0)
0-
1/
16
10
#110000
1;
1>
b1010 9
1*
00
#115000
1#
1&
b1011 !
b1011 @
1+
06
04
10
#120000
1:
1<
0;
0>
b1011 9
1(
0*
00
#125000
0#
0&
1%
1'
b1100 !
b1100 @
0+
1)
15
12
10
#130000
1;
1>
b1100 9
1*
00
#135000
1#
1&
b1101 !
b1101 @
1+
05
02
13
11
10
#140000
0:
0<
0;
0>
b1101 9
1,
0(
0*
00
#145000
0#
0&
0%
0'
b1110 !
b1110 @
0+
0)
1-
15
12
10
#150000
1;
1?
b1110 9
1*
00
#155000
1"
1&
b1111 !
b1111 @
1+
05
02
03
01
10
#160000
1:
1=
0;
0?
b1111 9
1(
0*
00
#165000
0"
0&
1$
1'
b10000 !
b10000 @
0+
1)
16
12
10
#170000
1;
1?
b10000 9
1*
00
#175000
1"
1&
b10001 !
b10001 @
1+
06
02
14
11
10
#180000
00
#185000
b10010 !
b10010 @
16
12
10
